{"_id": "kM306USBWCODTgC9", "name": "Wind Wall", "ownership": {"default": 0}, "type": "spell", "system": {"description": {"value": "<p>The strong wind keeps fog, smoke, and other gases at bay. Small or smaller flying creatures or objects can’t pass through the wall. Loose, lightweight materials brought into the wall fly upward. Arrows, bolts, and other ordinary projectiles launched at targets behind the wall are deflected upward and automatically miss. (Boulders hurled by giants or siege engines, and similar projectiles, are unaffected.) Creatures in gaseous form can’t pass through it.</p>", "chat": null, "unidentified": null}, "source": "Player's Handbook", "activation": {"type": "action", "cost": 1, "condition": null}, "duration": {"value": "1", "units": "minute"}, "cover": null, "target": {"value": null, "width": null, "units": "ft", "type": null}, "range": {"value": "120", "long": null, "units": "ft"}, "uses": {"value": null, "max": null, "per": null, "recovery": null}, "consume": {"type": null, "target": null, "amount": null}, "ability": null, "actionType": "spell", "attackBonus": null, "chatFlavor": null, "critical": {"threshold": null, "damage": null}, "damage": {"parts": [], "versatile": null}, "formula": null, "save": {"ability": null, "dc": null, "scaling": "spell"}, "level": "3", "school": "evo", "components": {"vocal": true, "somatic": true, "material": true, "ritual": false, "concentration": true}, "materials": {"value": "a tiny fan and a feather of exotic origin", "consumed": false, "cost": null, "supply": 0}, "preparation": {"mode": "prepared", "prepared": "false"}, "scaling": {"mode": null, "formula": null}}, "sort": 0, "flags": {}, "img": "", "effects": [], "folder": null, "_stats": {"systemId": "dnd5e", "systemVersion": "2.1.0", "coreVersion": "10.291"}}